ChangeLog.md
LICENSE
MANIFEST.in
README.md
requirements.txt
setup.py
skyhawk/__init__.py
skyhawk/cli.py
skyhawk.egg-info/PKG-INFO
skyhawk.egg-info/SOURCES.txt
skyhawk.egg-info/dependency_links.txt
skyhawk.egg-info/entry_points.txt
skyhawk.egg-info/requires.txt
skyhawk.egg-info/top_level.txt
skyhawk/commands/__init__.py
skyhawk/commands/cmd_capture.py
skyhawk/commands/cmd_clear.py
skyhawk/commands/cmd_init.py
skyhawk/commands/cmd_run.py
skyhawk/commands/cmd_train.py
skyhawk/commands/cmd_view.py
skyhawk/misc/__init__.py
skyhawk/misc/colors.py
skyhawk/services/__init__.py
skyhawk/services/capture.py
skyhawk/services/clear.py
skyhawk/services/detector.py
skyhawk/services/initialize.py
skyhawk/services/trainer.py
skyhawk/services/view.py
test/test_run.py