Metadata-Version: 2.1
Name: skyhawk
Version: 0.0.7
Summary: Skyhawk is a CLI tool that can run on any device with a camera to recognize faces. It built with open-cv & python
Home-page: https://github.com/devqueue/Skyhawk-cli.git
Author: Haziq Sayyed
Author-email: haziq.sayyed@gmail.com
License: Mozilla Public License 2.0
Platform: UNKNOWN
Classifier: Topic :: Security
Classifier: Development Status :: 4 - Beta
Classifier: Environment :: Console
Classifier: License :: OSI Approved :: Mozilla Public License 2.0 (MPL 2.0)
Classifier: Intended Audience :: End Users/Desktop
Classifier: Operating System :: OS Independent
Classifier: Programming Language :: Python :: 3.7
Requires-Python: >=3.8
